jupytalk/__init__.py
jupytalk/benchmark/__init__.py
jupytalk/benchmark/mlprediction.py
jupytalk/pres_helper/__init__.py
jupytalk/pres_helper/image.py
jupytalk/talk_examples/__init__.py
jupytalk/talk_examples/pydata2016.py
jupytalk/talk_examples/sklearn2019.py
jupytalk/talk_examples/treant_wrapper.py
jupytalk-0.3.613.dist-info/LICENSE.txt
jupytalk-0.3.613.dist-info/METADATA
jupytalk-0.3.613.dist-info/WHEEL
jupytalk-0.3.613.dist-info/top_level.txt
jupytalk-0.3.613.dist-info/RECORD
