Metadata-Version: 2.1
Name: jupytalk
Version: 0.3.613
Summary: Material for presentations. The documentation generation is using pyquickhelper.
Home-page: http://www.xavierdupre.fr/app/jupytalk/helpsphinx/index.html
Author: Xavier Dupré
Author-email: xavier.dupre@gmail.com
License: MIT
Download-URL: https://github.com/sdpython/jupytalk
Keywords: jupytalk,first name,last name
Platform: UNKNOWN
Classifier: Programming Language :: Python :: 3
Classifier: Intended Audience :: Developers
Classifier: Topic :: Scientific/Engineering
Classifier: Topic :: Education
Classifier: License :: OSI Approved :: MIT License
Classifier: Development Status :: 5 - Production/Stable
Requires-Dist: pyquickhelper (>=1.9)
Requires-Dist: jyquickhelper
Requires-Dist: cpyquickhelper (>=0.2.226)
